<?xml version="1.0" encoding="UTF-8"?>
<!-- DO NOT EDIT: This file was automatically generated by SpartanStormSorcery.py -->
<contentList>
    <content contentuid="h0da7ab0eg1b54ga29ag5592ga62dca0d73b0" version="1">Unarmored Defense</content>
    <content contentuid="ha991fabbgee23g74c5g9eedg66447057b567" version="1">Your body is as resilient as any armour. While not wearing armour, you add your Charisma &lt;LSTag Tooltip="AbilityModifier"&gt;Modifier&lt;/LSTag&gt; to your &lt;LSTag Tooltip="ArmourClass"&gt;Armour Class&lt;/LSTag&gt;.</content>
    <content contentuid="hd8f80c72g8e06ga35dg51a5g1c3e01b34c85" version="1">Storm Sorcerer's Spartan Gear</content>
    <content contentuid="h33403651g7c97g9e70g9f9dga4e2be9e17b6" version="1">Forged from blackened steel and reinforced with storm-weathered oak, this heavy chest bears the mark of a Spartan Storm Sorcerer. Its lid is secured by robust iron clasps, etched with subtle, angular lightning bolts that hint at the raw power contained within.</content>
    <content contentuid="h76da934cgf788g5507gbfb0gafd138b9b33e" version="1">Storm Sorcery: Hit Points</content>
    <content contentuid="h5c3c52f2gb6a3g78a2gae36g7178f03af588" version="1">Your &lt;LSTag Tooltip="HitPoints"&gt;hit point&lt;/LSTag&gt; maximum increases by 2 for each Sorcerer level.</content>
    <content contentuid="h224dff77g592fg531dg4115g474bafb3d308" version="1">Empowered Spells</content>
    <content contentuid="hce4eb357g48acg5232gf800gdf737669364e" version="1">When you cast a damaging spell, add your &lt;LSTag Tooltip="Charisma"&gt;Charisma&lt;/LSTag&gt; &lt;LSTag Tooltip="AbilityModifier"&gt;Modifier&lt;/LSTag&gt;" to the damage it deals.</content>
</contentList>